blibs/Colorize.py
blibs/__init__.py
blibs/traverseconf.py
blibs-1.1.0.dist-info/METADATA
blibs-1.1.0.dist-info/WHEEL
blibs-1.1.0.dist-info/top_level.txt
blibs-1.1.0.dist-info/RECORD
