Metadata-Version: 2.1
Name: blibs
Version: 1.1.0
Summary: Base python libs and helpers
Author-email: Damien Degois <damien@degois.info>
Project-URL: homepage, https://github.com/babs/blibs
Classifier: Topic :: Software Development :: Libraries :: Python Modules
Classifier: Programming Language :: Python :: 3 :: Only
